drawio_diagram_generator/__init__.py
drawio_diagram_generator/core.py
drawio_diagram_generator-1.0.1.dist-info/LICENSE
drawio_diagram_generator-1.0.1.dist-info/METADATA
drawio_diagram_generator-1.0.1.dist-info/WHEEL
drawio_diagram_generator-1.0.1.dist-info/top_level.txt
drawio_diagram_generator-1.0.1.dist-info/RECORD
