Metadata-Version: 2.1
Name: drawio-diagram-generator
Version: 1.0.1
Summary: A Python library for generating Draw.io diagrams programmatically
Home-page: https://github.com/yourusername/drawio-diagram-generator
Author: Your Name
Author-email: your.email@example.com
License: UNKNOWN
Project-URL: Bug Reports, https://github.com/yourusername/drawio-diagram-generator/issues
Project-URL: Source, https://github.com/yourusername/drawio-diagram-generator
Project-URL: Documentation, https://github.com/yourusername/drawio-diagram-generator#readme
Keywords: drawio,diagram,generator,xml,visualization
Platform: UNKNOWN
Classifier: Development Status :: 4 - Beta
Classifier: Intended Audience :: Developers
Classifier: License :: OSI Approved :: MIT License
Classifier: Operating System :: OS Independent
Classifier: Programming Language :: Python :: 3
Classifier: Programming Language :: Python :: 3.7
Classifier: Programming Language :: Python :: 3.8
Classifier: Programming Language :: Python :: 3.9
Classifier: Programming Language :: Python :: 3.10
Classifier: Programming Language :: Python :: 3.11
Classifier: Topic :: Software Development :: Libraries :: Python Modules
Classifier: Topic :: Multimedia :: Graphics :: Graphics Conversion
Requires-Python: >=3.7
License-File: LICENSE
Requires-Dist: Pillow>=8.0.0
